openskill/__init__.py
openskill/py.typed
openskill/models/__init__.py
openskill/models/common.py
openskill/models/weng_lin/__init__.py
openskill/models/weng_lin/bradley_terry_full.py
openskill/models/weng_lin/bradley_terry_part.py
openskill/models/weng_lin/common.py
openskill/models/weng_lin/plackett_luce.py
openskill/models/weng_lin/thurstone_mosteller_full.py
openskill/models/weng_lin/thurstone_mosteller_part.py
openskill-6.1.3.dist-info/licenses/LICENSE
openskill-6.1.3.dist-info/METADATA
openskill-6.1.3.dist-info/WHEEL
openskill-6.1.3.dist-info/top_level.txt
openskill-6.1.3.dist-info/RECORD
