Metadata-Version: 2.4
Name: openskill
Version: 6.1.3
Summary: Multiplayer Rating System. No Friction.
Author-email: Vivek Joshy <git@vivekjoshy.com>
Maintainer-email: Vivek Joshy <git@vivekjoshy.com>
License-Expression: MIT
Project-URL: Source, https://github.com/vivekjoshy/openskill.py
Project-URL: Documentation, https://openskill.me/en/stable
Project-URL: Changelog, https://github.com/vivekjoshy/openskill.py/blob/main/CHANGELOG.rst
Project-URL: Funding, https://github.com/sponsors/vivekjoshy
Project-URL: Tracker, https://github.com/vivekjoshy/openskill.py/issues
Keywords: ranking,trueskill,statistics,rating,math,rank
Classifier: Development Status :: 5 - Production/Stable
Classifier: Intended Audience :: Developers
Classifier: Natural Language :: English
Classifier: Operating System :: OS Independent
Classifier: Programming Language :: Python :: 3.10
Classifier: Programming Language :: Python :: 3.11
Classifier: Programming Language :: Python :: 3.12
Classifier: Programming Language :: Python :: 3.13
Classifier: Programming Language :: Python :: 3.14
Classifier: Programming Language :: Python :: Implementation :: CPython
Classifier: Programming Language :: Python :: Implementation :: PyPy
Requires-Python: ~=3.10
License-File: LICENSE
Provides-Extra: docs
Requires-Dist: sphinx~=8.1; extra == "docs"
Requires-Dist: nbsphinx~=0.9; extra == "docs"
Requires-Dist: pygments~=2.19; extra == "docs"
Requires-Dist: shibuya~=2025.2; extra == "docs"
Requires-Dist: ipykernel~=6.29; extra == "docs"
Requires-Dist: matplotlib~=3.10; extra == "docs"
Requires-Dist: myst-parser~=4.0; extra == "docs"
Requires-Dist: sphinx-intl~=2.3; extra == "docs"
Requires-Dist: sphinx-favicon~=1.0; extra == "docs"
Requires-Dist: sphinx-docsearch~=0.1; extra == "docs"
Requires-Dist: sphinx-copybutton~=0.5; extra == "docs"
Requires-Dist: sphinxext-opengraph~=0.9; extra == "docs"
Requires-Dist: sphinxcontrib-bibtex~=2.6; extra == "docs"
Requires-Dist: sphinx-autodoc-typehints~=3.0; extra == "docs"
Provides-Extra: tests
Requires-Dist: tox~=4.24; extra == "tests"
Requires-Dist: mypy~=1.15; extra == "tests"
Requires-Dist: pytest~=8.3; extra == "tests"
Requires-Dist: codecov~=2.1; extra == "tests"
Requires-Dist: coverage~=7.6; extra == "tests"
Requires-Dist: pytest-cov~=6.0; extra == "tests"
Provides-Extra: build
Requires-Dist: twine~=6.1; extra == "build"
Requires-Dist: build~=1.2; extra == "build"
Requires-Dist: isort~=6.0; extra == "build"
Requires-Dist: mypy[mypyc]~=1.15; extra == "build"
Requires-Dist: black[jupyter]~=25.1; extra == "build"
Requires-Dist: towncrier~=24.8; extra == "build"
Requires-Dist: bump-my-version~=1.1; extra == "build"
Provides-Extra: benchmark
Requires-Dist: rich~=14.0; extra == "benchmark"
Requires-Dist: tqdm~=4.67; extra == "benchmark"
Requires-Dist: pooch~=1.8; extra == "benchmark"
Requires-Dist: jsonlines~=4.0; extra == "benchmark"
Requires-Dist: scikit-learn~=1.6; extra == "benchmark"
Dynamic: license-file
